falcon_stats-0.5.dist-info/DESCRIPTION.rst
falcon_stats-0.5.dist-info/METADATA
falcon_stats-0.5.dist-info/RECORD
falcon_stats-0.5.dist-info/WHEEL
falcon_stats-0.5.dist-info/metadata.json
falcon_stats-0.5.dist-info/top_level.txt
falconstats/__init__.py
falconstats/middleware.py
falconstats/models.py
tests/__init__.py
tests/test_middleware.py
